niveshpy/__init__.py
niveshpy/database.py
niveshpy/exceptions.py
niveshpy/cli/__init__.py
niveshpy/cli/account.py
niveshpy/cli/main.py
niveshpy/cli/parse.py
niveshpy/cli/price.py
niveshpy/cli/security.py
niveshpy/cli/transaction.py
niveshpy/cli/utils/essentials.py
niveshpy/cli/utils/flags.py
niveshpy/cli/utils/inputs.py
niveshpy/cli/utils/logging.py
niveshpy/cli/utils/output.py
niveshpy/cli/utils/overrides.py
niveshpy/core/app.py
niveshpy/core/logging.py
niveshpy/core/parsers.py
niveshpy/core/providers.py
niveshpy/core/query/__init__.py
niveshpy/core/query/ast.py
niveshpy/core/query/parser.py
niveshpy/core/query/prepare.py
niveshpy/core/query/tokenizer.py
niveshpy/core/query/tokens.py
niveshpy/models/__init__.py
niveshpy/models/account.py
niveshpy/models/output.py
niveshpy/models/parser.py
niveshpy/models/price.py
niveshpy/models/provider.py
niveshpy/models/security.py
niveshpy/models/transaction.py
niveshpy/parsers/cas.py
niveshpy/providers/amfi.py
niveshpy/services/account.py
niveshpy/services/parsing.py
niveshpy/services/price.py
niveshpy/services/result.py
niveshpy/services/security.py
niveshpy/services/transaction.py
niveshpy-1.0.0a2.dist-info/METADATA
niveshpy-1.0.0a2.dist-info/WHEEL
niveshpy-1.0.0a2.dist-info/entry_points.txt
niveshpy-1.0.0a2.dist-info/licenses/LICENSE
niveshpy-1.0.0a2.dist-info/RECORD
